boonsdk/__init__.py
boonsdk/client.py
boonsdk/filters.py
boonsdk/search.py
boonsdk/training.py
boonsdk/util.py
boonsdk/app/__init__.py
boonsdk/app/analysis_app.py
boonsdk/app/asset_app.py
boonsdk/app/boon_app.py
boonsdk/app/boonlib_app.py
boonsdk/app/clip_app.py
boonsdk/app/dataset_app.py
boonsdk/app/datasource_app.py
boonsdk/app/field_app.py
boonsdk/app/job_app.py
boonsdk/app/model_app.py
boonsdk/app/project_app.py
boonsdk/app/webhook_app.py
boonsdk/entity/__init__.py
boonsdk/entity/analysis.py
boonsdk/entity/asset.py
boonsdk/entity/base.py
boonsdk/entity/boonlib.py
boonsdk/entity/clip.py
boonsdk/entity/dataset.py
boonsdk/entity/datasource.py
boonsdk/entity/exception.py
boonsdk/entity/field.py
boonsdk/entity/job.py
boonsdk/entity/model.py
boonsdk/entity/project.py
boonsdk/entity/storage.py
boonsdk/entity/webhook.py
boonsdk/func/__init__.py
boonsdk/func/env.py
boonsdk/func/proxy.py
boonsdk/func/response.py
boonsdk/tools/boonctl/__init__.py
boonsdk/tools/boonctl/asset.py
boonsdk/tools/boonctl/boonlib.py
boonsdk/tools/boonctl/dataset.py
boonsdk/tools/boonctl/field.py
boonsdk/tools/boonctl/main.py
boonsdk/tools/boonctl/model.py
boonsdk-1.4.7.data/scripts/boonctl
boonsdk-1.4.7.dist-info/LICENSE.txt
boonsdk-1.4.7.dist-info/METADATA
boonsdk-1.4.7.dist-info/WHEEL
boonsdk-1.4.7.dist-info/top_level.txt
boonsdk-1.4.7.dist-info/RECORD
